engression_pytorch/__init__.py
engression_pytorch/main.py
engression_pytorch-0.1.3.dist-info/METADATA
engression_pytorch-0.1.3.dist-info/WHEEL
engression_pytorch-0.1.3.dist-info/licenses/LICENSE
engression_pytorch-0.1.3.dist-info/RECORD
