Metadata-Version: 2.4
Name: engression-pytorch
Version: 0.1.3
Summary: The engression loss (energy score) proposed by Shen et al. for distributional regression with a few convenient wrappers, in Pytorch.
Project-URL: Homepage, https://pypi.org/project/engression-pytorch/
Project-URL: Repository, https://github.com/emiliocantuc/engression-pytorch
Author-email: Emilio Cantu <ecantuc@umich.edu>
License-File: LICENSE
Requires-Python: >=3.9
Requires-Dist: einops>=0.8.1
Requires-Dist: torch>=2.7.0
Provides-Extra: examples
Requires-Dist: matplotlib; extra == 'examples'
Provides-Extra: test
Requires-Dist: pytest; extra == 'test'
